ppm/__init__.py
ppm/ppm.py
ppm_cmd-0.1.4.dist-info/LICENSE
ppm_cmd-0.1.4.dist-info/METADATA
ppm_cmd-0.1.4.dist-info/WHEEL
ppm_cmd-0.1.4.dist-info/entry_points.txt
ppm_cmd-0.1.4.dist-info/RECORD
