Metadata-Version: 2.1
Name: ppm-cmd
Version: 0.1.4
Summary: python project manager
Author: manishshettym
Author-email: manishs@berkeley.edu
Requires-Python: >=3.9,<4.0
Classifier: Programming Language :: Python :: 3
Classifier: Programming Language :: Python :: 3.9
Classifier: Programming Language :: Python :: 3.10
Classifier: Programming Language :: Python :: 3.11
Requires-Dist: poetry (>=1.6.1,<2.0.0)
Requires-Dist: questionary (>=2.0.1,<3.0.0)
Requires-Dist: rich (>=13.6.0,<14.0.0)
Requires-Dist: typer (>=0.9.0,<0.10.0)
